bac_detect/__init__.py
bac_detect/_detect_obfuscation.py
bac_detect/api.py
bac_detect/backdoor_detector.py
bac_detect/ml_detector.py
bac_detect/patterns.json
bac_detect-1.4.0.dist-info/entry_points.txt
bac_detect-1.4.0.dist-info/LICENSE
bac_detect-1.4.0.dist-info/METADATA
bac_detect-1.4.0.dist-info/WHEEL
bac_detect-1.4.0.dist-info/RECORD
