Metadata-Version: 2.3
Name: bac_detect
Version: 1.4.0
Summary: Detect backdoors in Python, JS, PHP and TypeScript code
License: MIT
Author: Ruslan
Author-email: ruslan@example.com
Requires-Python: >=3.8,<4.0
Classifier: Development Status :: 4 - Beta
Classifier: Intended Audience :: Developers
Classifier: Intended Audience :: Information Technology
Classifier: License :: OSI Approved :: MIT License
Classifier: Operating System :: OS Independent
Classifier: Programming Language :: Python :: 3
Classifier: Programming Language :: Python :: 3.8
Classifier: Programming Language :: Python :: 3.9
Classifier: Programming Language :: Python :: 3.10
Classifier: Programming Language :: Python :: 3.11
Classifier: Programming Language :: Python :: 3.12
Classifier: Programming Language :: Python :: 3.13
Classifier: Topic :: Security
Requires-Dist: bandit (>=1.7.0)
Requires-Dist: concurrent-log-handler (>=0.9.20)
Requires-Dist: esprima (>=4.0.1)
Requires-Dist: flask (>=2.0.0)
Requires-Dist: joblib (>=1.1.0)
Requires-Dist: numpy (>=1.19.0)
Requires-Dist: pylint (>=2.13.0)
Requires-Dist: scikit-learn (>=1.0.0)
Requires-Dist: tqdm (>=4.0.0)
Requires-Dist: werkzeug (>=2.0.0)
Project-URL: Repository, https://github.com/ruslan-user/bac_detect
